python_potion/__main__.py
python_potion/buffering.py
python_potion/client.py
python_potion/common.py
python_potion/converter.py
python_potion/decode_benchmark.py
python_potion/decoder.py
python_potion-0.4.0.post0.dist-info/licenses/LICENSE
python_potion-0.4.0.post0.dist-info/METADATA
python_potion-0.4.0.post0.dist-info/WHEEL
python_potion-0.4.0.post0.dist-info/top_level.txt
python_potion-0.4.0.post0.dist-info/RECORD
