Metadata-Version: 2.4
Name: python_potion
Version: 0.4.0.post0
Summary: Live video inference 
Author: Roman Arzumanyan
Author-email: Roman Arzumanyan <roman.arzum@gmail.com>
License-File: LICENSE
Dynamic: author
Dynamic: description
Dynamic: description-content-type
Dynamic: license-file
